ccpycounts/__init__.py
ccpycounts/ccpycounts.py
ccpycounts/plotting.py
ccpycounts-0.1.0.dist-info/LICENSE
ccpycounts-0.1.0.dist-info/METADATA
ccpycounts-0.1.0.dist-info/WHEEL
ccpycounts-0.1.0.dist-info/RECORD
